musib/__init__.py
musib/data/__init__.py
musib/data/download_from_source.py
musib/data/process_data.py
musib/data/standardize_data.py
musib/encoders/__init__.py
musib/encoders/encoders.py
musib/features/__init__.py
musib/features/dataset.py
musib/features/transforms.py
musib/models/arnn.py
musib/models/inpaintnet.py
musib/models/sketchnet.py
musib/models/sketchnetv2.py
musib/models/vli.py
musib/models/vaes/measurevae.py
musib/models/vaes/sketchvae.py
musib/models/vaes/sketchvae_v2.py
musib/transforms/__init__.py
musib/transforms/transforms.py
musib/visualization/plot_metrics.py
musib-0.0.3.dist-info/LICENSE
musib-0.0.3.dist-info/METADATA
musib-0.0.3.dist-info/WHEEL
musib-0.0.3.dist-info/top_level.txt
musib-0.0.3.dist-info/RECORD
