Metadata-Version: 2.1
Name: musib
Version: 0.0.3
Summary: Python library for building and evaluation/benchmarking of Automated Music Generation models
Author-email: Mauricio Araneda-Hernandez <mauricio.araneda.h@gmail.com>
Project-URL: Homepage, https://github.com/maranedah/musib
Project-URL: Bug Tracker, https://github.com/maranedah/maranedah/issues
Classifier: Programming Language :: Python :: 3
Classifier: License :: OSI Approved :: MIT License
Classifier: Operating System :: OS Independent
Requires-Python: >=3.7
License-File: LICENSE
